django_insect/__init__.py
django_insect/admin.py
django_insect/apps.py
django_insect/proxy.py
django_insect-0.0.3.dist-info/WHEEL
django_insect-0.0.3.dist-info/METADATA
django_insect-0.0.3.dist-info/RECORD
